flexible_dict/__init__.py
flexible_dict/__main__.py
flexible_dict/_dist_ver.py
flexible_dict/adapter.py
flexible_dict/json_object.py
flexible_dict/utils.py
flexible_dict/version.py
flexible_dict/script/__init__.py
flexible_dict/script/class_builder.py
flexible_dict-2.2.0.dist-info/METADATA
flexible_dict-2.2.0.dist-info/WHEEL
flexible_dict-2.2.0.dist-info/top_level.txt
flexible_dict-2.2.0.dist-info/RECORD
