Metadata-Version: 2.4
Name: flexible_dict
Version: 2.2.0
Summary: A flexible way to access dict data instead of built-in dict.
Author-email: darkpeath <darkpeath@gmail.com>
Project-URL: Homepage, https://github.com/darkpeath/flexible_dict
Requires-Dist: dataclasses; python_version < "3.7"
Requires-Dist: typing_extensions; python_version < "3.8"
